graphs_for_economics/__init__.py
graphs_for_economics/_modidx.py
graphs_for_economics/core.py
graphs_for_economics-0.0.5.dist-info/LICENSE
graphs_for_economics-0.0.5.dist-info/METADATA
graphs_for_economics-0.0.5.dist-info/WHEEL
graphs_for_economics-0.0.5.dist-info/entry_points.txt
graphs_for_economics-0.0.5.dist-info/top_level.txt
graphs_for_economics-0.0.5.dist-info/RECORD
